{
  "persons": [

  ],
  "organizations": [

  ],
  "areas": [
    {
      "id": "Q2933",
      "identifiers": [
        {
          "scheme": "MS_FB",
          "identifier": "country:py/distrito-capital:distrito-capital-de-paraguay"
        },
        {
          "scheme": "wikidata",
          "identifier": "Q2933"
        }
      ],
      "associated_wikidata_positions": [
        "Q51831955",
        "Q51842240"
      ],
      "type": {
        "lang:es_LA": "capital",
        "lang:gn_PY": "tavusu",
        "lang:en_US": "capital"
      },
      "name": {
        "lang:es_LA": "Distrito Capital de Paraguay"
      },
      "parent_id": "Q733"
    },
    {
      "id": "Q733",
      "identifiers": [
        {
          "scheme": "MS_FB",
          "identifier": "country:py"
        },
        {
          "scheme": "wikidata",
          "identifier": "Q733"
        }
      ],
      "associated_wikidata_positions": [
        "Q34071"
      ],
      "type": {
        "lang:es_LA": "país",
        "lang:gn_PY": "tetã",
        "lang:en_US": "country"
      },
      "name": {
        "lang:en_US": "Republic of Paraguay",
        "lang:es_LA": "República del Paraguay"
      },
      "parent_id": null
    }
  ],
  "memberships": [

  ]
}
